napari_annotator/__init__.py
napari_annotator/_annotation_entry.py
napari_annotator/_annotations_list_widget.py
napari_annotator/_dock_widget.py
napari_annotator/_version.py
napari_annotator/napari.yaml
napari_annotator/redo-arrow-icon.svg
napari_annotator/_tests/__init__.py
napari_annotator/_tests/test_dock_widget.py
napari_annotator-0.1.1.dist-info/LICENSE
napari_annotator-0.1.1.dist-info/METADATA
napari_annotator-0.1.1.dist-info/WHEEL
napari_annotator-0.1.1.dist-info/entry_points.txt
napari_annotator-0.1.1.dist-info/top_level.txt
napari_annotator-0.1.1.dist-info/RECORD
