Metadata-Version: 2.1
Name: napari-annotator
Version: 0.1.1
Summary: A lightweight plugin extending label layer control
Author: Loïc Sauteur
Author-email: loic.sauteur@unibas.ch
License: 
Project-URL: Bug Tracker, https://github.com/loicsauteur/napari-annotator/issues
Project-URL: Documentation, https://github.com/loicsauteur/napari-annotator#README.md
Project-URL: Source Code, https://github.com/loicsauteur/napari-annotator
Project-URL: User Support, https://github.com/loicsauteur/napari-annotator/issues
Classifier: Development Status :: 2 - Pre-Alpha
Classifier: Framework :: napari
Classifier: Intended Audience :: Developers
Classifier: License :: OSI Approved :: BSD License
Classifier: Operating System :: OS Independent
Classifier: Programming Language :: Python
Classifier: Programming Language :: Python :: 3
Classifier: Programming Language :: Python :: 3 :: Only
Classifier: Programming Language :: Python :: 3.9
Classifier: Programming Language :: Python :: 3.10
Classifier: Programming Language :: Python :: 3.11
Classifier: Programming Language :: Python :: 3.12
Classifier: Topic :: Scientific/Engineering :: Image Processing
Requires-Python: >=3.9
License-File: LICENSE
Requires-Dist: numpy
Requires-Dist: magicgui
Requires-Dist: qtpy
Requires-Dist: scikit-image
Requires-Dist: napari>=0.5.5
Provides-Extra: testing
Requires-Dist: tox; extra == "testing"
Requires-Dist: pytest; extra == "testing"
Requires-Dist: pytest-cov; extra == "testing"
Requires-Dist: pytest-qt; extra == "testing"
Requires-Dist: napari; extra == "testing"
Requires-Dist: pyqt5; extra == "testing"
